feincms_cleanse/__init__.py
feincms_cleanse/models.py
feincms_cleanse/tests/__init__.py
feincms_cleanse/tests/test_cleanse.py
feincms_cleanse-7.dist-info/DESCRIPTION.rst
feincms_cleanse-7.dist-info/METADATA
feincms_cleanse-7.dist-info/RECORD
feincms_cleanse-7.dist-info/WHEEL
feincms_cleanse-7.dist-info/metadata.json
feincms_cleanse-7.dist-info/top_level.txt
