Metadata-Version: 2.0
Name: feincms-cleanse
Version: 7
Summary: Default HTML cleansing in FeinCMS
Home-page: http://github.com/feincms/feincms-cleanse/
Author: Matthias Kestenholz
Author-email: mk@feinheit.ch
License: BSD License
Platform: OS Independent
Classifier: Development Status :: 5 - Production/Stable
Classifier: Environment :: Web Environment
Classifier: Framework :: Django
Classifier: Intended Audience :: Developers
Classifier: License :: OSI Approved :: BSD License
Classifier: Operating System :: OS Independent
Classifier: Programming Language :: Python
Classifier: Topic :: Internet :: WWW/HTTP :: Dynamic Content
Classifier: Topic :: Software Development
Requires-Dist: beautifulsoup4
Requires-Dist: lxml (>=3)
